ecanvci/__init__.py
ecanvci/can_record.py
ecanvci/common.py
ecanvci/ecanvci.py
ecanvci/helper.py
ecanvci/dll/CHUSBDLL64.dll
ecanvci/dll/ECanVci64.dll
ecanvci/dll/ECanVci64.lib
tests/__init__.py
tests/test_ecanvci.py
tests/test_helper.py
ecanvci-1.3.1.dist-info/LICENSE
ecanvci-1.3.1.dist-info/METADATA
ecanvci-1.3.1.dist-info/WHEEL
ecanvci-1.3.1.dist-info/top_level.txt
ecanvci-1.3.1.dist-info/RECORD
