Metadata-Version: 2.1
Name: ecanvci
Version: 1.3.1
Summary: python interface for GCAN USB to CAN device (ECanVci)
Home-page: https://github.com/xavieryin/ecanvci
Author: Xavier Yin
Author-email: bug313@gmail.com
License: UNKNOWN
Project-URL: Bug Tracker, https://github.com/xavieryin/ecanvci/issues
Platform: UNKNOWN
Classifier: Programming Language :: Python :: 3
Classifier: License :: OSI Approved :: MIT License
Classifier: Operating System :: OS Independent
Requires-Python: >=3.6
License-File: LICENSE
